Metadata-Version: 2.4
Name: django-python3-ldap-with-atz
Version: 0.15.10
Summary: Django LDAP user authentication backend for Python 3, with authorization
Project-URL: Homepage, https://github.com/henschkowski/django-python3-ldap_with_authorization
Author-email: Ralf Henschkowski <ralf.henschkowski@gmail.com>, Dave Hall <dave@etianen.com>
Maintainer-email: Ralf Henschkowski <ralf.henschkowski@gmail.com>
License-Expression: BSD-3-Clause
License-File: LICENSE
Classifier: Development Status :: 4 - Beta
Classifier: Environment :: Web Environment
Classifier: Framework :: Django
Classifier: Intended Audience :: Developers
Classifier: License :: OSI Approved :: BSD License
Classifier: Operating System :: OS Independent
Classifier: Programming Language :: Python
Classifier: Programming Language :: Python :: 3.12
Requires-Python: >=3.12
Requires-Dist: django>=1.11
Requires-Dist: ldap3<3,>=2.5
Requires-Dist: pyasn1<0.6,>=0.4.6
